setup.py
jogging/__init__.py
jogging/admin.py
jogging/handlers.py
jogging/middleware.py
jogging/models.py
jogging.egg-info/PKG-INFO
jogging.egg-info/SOURCES.txt
jogging.egg-info/dependency_links.txt
jogging.egg-info/top_level.txt