Metadata-Version: 1.0
Name: jogging
Version: 0.2.2
Summary: Jogging makes logging in django easier
Home-page: UNKNOWN
Author: Zain
Author-email: zain@inzain.net
License: UNKNOWN
Platform: UNKNOWN
